my_library/__init__.py
my_library/example.py
my_library/other_modules.py
rohit_python_utils-0.1.dist-info/METADATA
rohit_python_utils-0.1.dist-info/WHEEL
rohit_python_utils-0.1.dist-info/entry_points.txt
rohit_python_utils-0.1.dist-info/top_level.txt
rohit_python_utils-0.1.dist-info/RECORD
