Metadata-Version: 2.4
Name: rohit-python-utils
Version: 0.1
Summary: A utility library for Python to perform common tasks
Home-page: https://github.com/yourusername/rohit-python-utils
Author: Krishnamurthy Chandran
Author-email: rohtihkrishna112002@gmail.com
Classifier: Programming Language :: Python :: 3
Classifier: License :: OSI Approved :: MIT License
Classifier: Operating System :: OS Independent
Requires-Python: >=3.6
Dynamic: author
Dynamic: author-email
Dynamic: classifier
Dynamic: description-content-type
Dynamic: home-page
Dynamic: requires-python
Dynamic: summary
